{"timeRange":[1586124000000,1586210400000],"engine":"random-OCA-engine-0","executions":[{"time":{"start":1586182971078,"deploy":1586182972194,"undeploy":1586183614814,"end":1586183661501},"duration":{"deploy":659,"execution":642620,"undeploy":47144,"total":690423},"status":{"management":"successful","execution":"successful"},"layout":[{"componentId":"7b300e43-27aa-4c08-9545-f06934b7d0cf","status":"","nbRows":0,"nbRejectedRows":0,"duration":0,"error":""},{"componentId":"82eed63e-f20f-4280-a643-1d4d708b0cb8","status":"","nbRows":0,"nbRejectedRows":0,"duration":0,"error":""}],"context":{"executionId":"25c7d221-3c18-4c1b-ab11-0ef4a6482f7b","artifact":{"id":"6bf4d0a5-8e3c-4726-99be-72dd20e374e9","name":"Replication","version":"1.11","type":"pipeline"},"task":{"id":"d9869e24-f7b9-4d9b-9f52-ae6f1e623245","name":"random-OCA-task-Replication","version":"1.0","params":{"param1":"whatever"}},"workspace":{"id":"fcfa35cb-526d-414e-994a-1822d8b62c28","name":"random-OCA"},"environment":{"id":"27fdf8c9-962e-4a89-b614-6be5c4309b40","name":"prod"},"engine":{"id":"6006997c-dcb7-488d-b11b-9864980f1019","name":"random-OCA-engine-0"},"cluster":{"id":"77d7d870-4503-4e47-9f35-3156a1ac7bfd","name":"cluster-random-OCA","runProfile":""},"tags":[],"runType":"api"},"fingerprint":{"cpu":{"min":20,"max":84,"mean":24},"memory":{"min":4,"max":185,"mean":68},"logs":[{"timestamp":1586182920000,"cpu":0,"memory":0},{"timestamp":1586183040000,"cpu":63,"memory":94},{"timestamp":1586183160000,"cpu":30,"memory":57},{"timestamp":1586183280000,"cpu":66,"memory":144},{"timestamp":1586183400000,"cpu":37,"memory":156},{"timestamp":1586183520000,"cpu":59,"memory":38},{"timestamp":1586183640000,"cpu":0,"memory":0}]}},{"time":{"start":1586178778825,"end":1586178778825},"duration":{"deploy":0,"execution":0,"undeploy":0,"total":0},"status":{"management":"deploy_failure","execution":""},"layout":[{"componentId":"6d48174b-9f75-46df-b780-09905c60e2f7","status":"","nbRows":0,"nbRejectedRows":0,"duration":0,"error":""},{"componentId":"07a13a82-07e9-4bf5-8f84-847f1598b7dd","status":"","nbRows":0,"nbRejectedRows":0,"duration":0,"error":""}],"context":{"executionId":"37458a6e-dc1c-4da9-b4b9-20932bac4ca5","artifact":{"id":"ca71143f-56e4-4d22-a4bc-aaf6878fb618","name":"Demo","version":"1.12","type":"pipeline"},"task":{"id":"5ddee1b1-dca4-4999-a0f7-f80f804cfd71","name":"random-OCA-task-Demo","version":"1.0","params":{"param1":"whatever"}},"workspace":{"id":"fcfa35cb-526d-414e-994a-1822d8b62c28","name":"random-OCA"},"environment":{"id":"27fdf8c9-962e-4a89-b614-6be5c4309b40","name":"prod"},"engine":{"id":"6006997c-dcb7-488d-b11b-9864980f1019","name":"random-OCA-engine-0"},"cluster":{"id":"77d7d870-4503-4e47-9f35-3156a1ac7bfd","name":"cluster-random-OCA","runProfile":""},"tags":[],"runType":"webhook"},"retries":[{"engine":{"id":"6006997c-dcb7-488d-b11b-9864980f1019","name":"random-OCA-engine-0"},"time":1586177878825},{"engine":{"id":"6006997c-dcb7-488d-b11b-9864980f1019","name":"random-OCA-engine-0"},"time":1586178178825},{"engine":{"id":"6006997c-dcb7-488d-b11b-9864980f1019","name":"random-OCA-engine-0"},"time":1586178478825},{"engine":{"id":"6006997c-dcb7-488d-b11b-9864980f1019","name":"random-OCA-engine-0"},"time":1586178778825}],"fingerprint":{"cpu":{"min":18,"max":75,"mean":41},"memory":{"min":10,"max":144,"mean":81},"logs":[{"timestamp":1586178720000,"cpu":0,"memory":0},{"timestamp":1586178720000,"cpu":0,"memory":0}]}},{"time":{"start":1586175469752,"deploy":1586175519857,"undeploy":1586182204307,"end":1586182246707},"duration":{"deploy":38330,"execution":6684450,"undeploy":54175,"total":6776955},"status":{"management":"successful","execution":"successful"},"layout":[{"componentId":"ed3b4973-a6a2-4374-91d2-90b1a162fcb0","status":"","nbRows":0,"nbRejectedRows":0,"duration":0,"error":""},{"componentId":"2b45cb7b-8131-448a-a139-69a4aba04a07","status":"","nbRows":0,"nbRejectedRows":0,"duration":0,"error":""}],"context":{"executionId":"9b7145a9-f41e-48d1-a221-ae08bf54b90e","artifact":{"id":"31bb51c6-e879-48e9-a21f-df738cdeb6f2","name":"Business","version":"1.4","type":"pipeline"},"task":{"id":"cd98870c-3d12-4633-959d-1273c56466c0","name":"random-OCA-task-Business","version":"1.0","params":{"param1":"whatever"}},"workspace":{"id":"fcfa35cb-526d-414e-994a-1822d8b62c28","name":"random-OCA"},"environment":{"id":"27fdf8c9-962e-4a89-b614-6be5c4309b40","name":"prod"},"engine":{"id":"6006997c-dcb7-488d-b11b-9864980f1019","name":"random-OCA-engine-0"},"cluster":{"id":"77d7d870-4503-4e47-9f35-3156a1ac7bfd","name":"cluster-random-OCA","runProfile":""},"tags":[],"runType":"webhook"},"fingerprint":{"cpu":{"min":13,"max":97,"mean":61},"memory":{"min":49,"max":248,"mean":88},"logs":[{"timestamp":1586175360000,"cpu":0,"memory":0},{"timestamp":1586175480000,"cpu":28,"memory":86},{"timestamp":1586175600000,"cpu":90,"memory":164},{"timestamp":1586175720000,"cpu":56,"memory":134},{"timestamp":1586175840000,"cpu":50,"memory":156},{"timestamp":1586175960000,"cpu":45,"memory":77},{"timestamp":1586176080000,"cpu":77,"memory":185},{"timestamp":1586176200000,"cpu":48,"memory":198},{"timestamp":1586176320000,"cpu":50,"memory":157},{"timestamp":1586176440000,"cpu":28,"memory":106},{"timestamp":1586176560000,"cpu":24,"memory":218},{"timestamp":1586176680000,"cpu":74,"memory":167},{"timestamp":1586176800000,"cpu":49,"memory":68},{"timestamp":1586176920000,"cpu":37,"memory":170},{"timestamp":1586177040000,"cpu":22,"memory":118},{"timestamp":1586177160000,"cpu":32,"memory":187},{"timestamp":1586177280000,"cpu":62,"memory":203},{"timestamp":1586177400000,"cpu":66,"memory":205},{"timestamp":1586177520000,"cpu":56,"memory":214},{"timestamp":1586177640000,"cpu":28,"memory":120},{"timestamp":1586177760000,"cpu":29,"memory":131},{"timestamp":1586177880000,"cpu":19,"memory":141},{"timestamp":1586178000000,"cpu":50,"memory":155},{"timestamp":1586178120000,"cpu":89,"memory":78},{"timestamp":1586178240000,"cpu":65,"memory":240},{"timestamp":1586178360000,"cpu":50,"memory":243},{"timestamp":1586178480000,"cpu":95,"memory":104},{"timestamp":1586178600000,"cpu":40,"memory":62},{"timestamp":1586178720000,"cpu":96,"memory":187},{"timestamp":1586178840000,"cpu":20,"memory":215},{"timestamp":1586178960000,"cpu":26,"memory":117},{"timestamp":1586179080000,"cpu":16,"memory":240},{"timestamp":1586179200000,"cpu":70,"memory":153},{"timestamp":1586179320000,"cpu":53,"memory":101},{"timestamp":1586179440000,"cpu":41,"memory":194},{"timestamp":1586179560000,"cpu":46,"memory":104},{"timestamp":1586179680000,"cpu":27,"memory":183},{"timestamp":1586179800000,"cpu":66,"memory":190},{"timestamp":1586179920000,"cpu":52,"memory":190},{"timestamp":1586180040000,"cpu":21,"memory":69},{"timestamp":1586180160000,"cpu":13,"memory":211},{"timestamp":1586180280000,"cpu":15,"memory":222},{"timestamp":1586180400000,"cpu":78,"memory":77},{"timestamp":1586180520000,"cpu":28,"memory":101},{"timestamp":1586180640000,"cpu":24,"memory":54},{"timestamp":1586180760000,"cpu":87,"memory":225},{"timestamp":1586180880000,"cpu":92,"memory":203},{"timestamp":1586181000000,"cpu":65,"memory":79},{"timestamp":1586181120000,"cpu":15,"memory":210},{"timestamp":1586181240000,"cpu":76,"memory":236},{"timestamp":1586181360000,"cpu":31,"memory":153},{"timestamp":1586181480000,"cpu":27,"memory":247},{"timestamp":1586181600000,"cpu":13,"memory":175},{"timestamp":1586181720000,"cpu":60,"memory":244},{"timestamp":1586181840000,"cpu":42,"memory":248},{"timestamp":1586181960000,"cpu":43,"memory":148},{"timestamp":1586182080000,"cpu":87,"memory":61},{"timestamp":1586182200000,"cpu":0,"memory":0}]}},{"time":{"start":1586143041715,"deploy":1586143057884,"undeploy":1586145492000,"end":1586145522188},"duration":{"deploy":26248,"execution":2434116,"undeploy":20109,"total":2480473},"status":{"management":"successful","execution":"successful"},"layout":[{"componentId":"3dd9d25e-9ff2-464d-9283-e1bc445a8695","status":"","nbRows":0,"nbRejectedRows":0,"duration":0,"error":""},{"componentId":"6654504d-deaa-419e-950b-3234eef1b290","status":"","nbRows":0,"nbRejectedRows":0,"duration":0,"error":""}],"context":{"executionId":"8dd2bbf6-6d67-4c6c-b422-fd6ca8677d1f","artifact":{"id":"31bb51c6-e879-48e9-a21f-df738cdeb6f2","name":"Business","version":"1.4","type":"pipeline"},"task":{"id":"cd98870c-3d12-4633-959d-1273c56466c0","name":"random-OCA-task-Business","version":"1.0","params":{"param1":"whatever"}},"workspace":{"id":"fcfa35cb-526d-414e-994a-1822d8b62c28","name":"random-OCA"},"environment":{"id":"27fdf8c9-962e-4a89-b614-6be5c4309b40","name":"prod"},"engine":{"id":"6006997c-dcb7-488d-b11b-9864980f1019","name":"random-OCA-engine-0"},"cluster":{"id":"77d7d870-4503-4e47-9f35-3156a1ac7bfd","name":"cluster-random-OCA","runProfile":""},"tags":[],"runType":"webhook"},"fingerprint":{"cpu":{"min":13,"max":90,"mean":31},"memory":{"min":37,"max":142,"mean":89},"logs":[{"timestamp":1586142960000,"cpu":0,"memory":0},{"timestamp":1586143080000,"cpu":79,"memory":96},{"timestamp":1586143200000,"cpu":26,"memory":75},{"timestamp":1586143320000,"cpu":21,"memory":94},{"timestamp":1586143440000,"cpu":75,"memory":127},{"timestamp":1586143560000,"cpu":83,"memory":111},{"timestamp":1586143680000,"cpu":32,"memory":141},{"timestamp":1586143800000,"cpu":71,"memory":122},{"timestamp":1586143920000,"cpu":36,"memory":50},{"timestamp":1586144040000,"cpu":51,"memory":114},{"timestamp":1586144160000,"cpu":24,"memory":73},{"timestamp":1586144280000,"cpu":22,"memory":115},{"timestamp":1586144400000,"cpu":39,"memory":115},{"timestamp":1586144520000,"cpu":85,"memory":141},{"timestamp":1586144640000,"cpu":20,"memory":126},{"timestamp":1586144760000,"cpu":85,"memory":54},{"timestamp":1586144880000,"cpu":62,"memory":49},{"timestamp":1586145000000,"cpu":65,"memory":123},{"timestamp":1586145120000,"cpu":70,"memory":78},{"timestamp":1586145240000,"cpu":80,"memory":107},{"timestamp":1586145360000,"cpu":47,"memory":61},{"timestamp":1586145480000,"cpu":0,"memory":0}]}},{"time":{"start":1586134989654,"deploy":1586135041695,"undeploy":1586140126924,"end":1586140128109},"duration":{"deploy":38497,"execution":5085229,"undeploy":14729,"total":5138455},"status":{"management":"successful","execution":"successful"},"layout":[{"componentId":"a5ce1551-5c5a-47d7-a3db-3b8315a9b27f","status":"","nbRows":0,"nbRejectedRows":0,"duration":0,"error":""},{"componentId":"cb34bfb1-56f8-4297-a5d9-ab7fc0b9ab51","status":"","nbRows":0,"nbRejectedRows":0,"duration":0,"error":""}],"context":{"executionId":"3a583f4d-6aea-41c0-a074-cb06148f1d79","artifact":{"id":"ca71143f-56e4-4d22-a4bc-aaf6878fb618","name":"Demo","version":"1.12","type":"pipeline"},"task":{"id":"5ddee1b1-dca4-4999-a0f7-f80f804cfd71","name":"random-OCA-task-Demo","version":"1.0","params":{"param1":"whatever"}},"workspace":{"id":"fcfa35cb-526d-414e-994a-1822d8b62c28","name":"random-OCA"},"environment":{"id":"27fdf8c9-962e-4a89-b614-6be5c4309b40","name":"prod"},"engine":{"id":"6006997c-dcb7-488d-b11b-9864980f1019","name":"random-OCA-engine-0"},"cluster":{"id":"77d7d870-4503-4e47-9f35-3156a1ac7bfd","name":"cluster-random-OCA","runProfile":""},"tags":[],"runType":"webhook"},"fingerprint":{"cpu":{"min":6,"max":76,"mean":26},"memory":{"min":26,"max":138,"mean":67},"logs":[{"timestamp":1586134920000,"cpu":0,"memory":0},{"timestamp":1586135040000,"cpu":37,"memory":59},{"timestamp":1586135160000,"cpu":72,"memory":39},{"timestamp":1586135280000,"cpu":22,"memory":36},{"timestamp":1586135400000,"cpu":10,"memory":27},{"timestamp":1586135520000,"cpu":65,"memory":39},{"timestamp":1586135640000,"cpu":14,"memory":125},{"timestamp":1586135760000,"cpu":62,"memory":60},{"timestamp":1586135880000,"cpu":73,"memory":75},{"timestamp":1586136000000,"cpu":53,"memory":30},{"timestamp":1586136120000,"cpu":42,"memory":35},{"timestamp":1586136240000,"cpu":51,"memory":43},{"timestamp":1586136360000,"cpu":41,"memory":60},{"timestamp":1586136480000,"cpu":26,"memory":27},{"timestamp":1586136600000,"cpu":14,"memory":77},{"timestamp":1586136720000,"cpu":21,"memory":117},{"timestamp":1586136840000,"cpu":17,"memory":47},{"timestamp":1586136960000,"cpu":9,"memory":67},{"timestamp":1586137080000,"cpu":31,"memory":51},{"timestamp":1586137200000,"cpu":7,"memory":46},{"timestamp":1586137320000,"cpu":43,"memory":81},{"timestamp":1586137440000,"cpu":29,"memory":34},{"timestamp":1586137560000,"cpu":60,"memory":28},{"timestamp":1586137680000,"cpu":30,"memory":34},{"timestamp":1586137800000,"cpu":70,"memory":136},{"timestamp":1586137920000,"cpu":30,"memory":120},{"timestamp":1586138040000,"cpu":70,"memory":64},{"timestamp":1586138160000,"cpu":36,"memory":98},{"timestamp":1586138280000,"cpu":11,"memory":136},{"timestamp":1586138400000,"cpu":7,"memory":30},{"timestamp":1586138520000,"cpu":27,"memory":95},{"timestamp":1586138640000,"cpu":49,"memory":73},{"timestamp":1586138760000,"cpu":46,"memory":57},{"timestamp":1586138880000,"cpu":19,"memory":124},{"timestamp":1586139000000,"cpu":7,"memory":35},{"timestamp":1586139120000,"cpu":43,"memory":54},{"timestamp":1586139240000,"cpu":54,"memory":119},{"timestamp":1586139360000,"cpu":51,"memory":122},{"timestamp":1586139480000,"cpu":22,"memory":55},{"timestamp":1586139600000,"cpu":29,"memory":64},{"timestamp":1586139720000,"cpu":14,"memory":47},{"timestamp":1586139840000,"cpu":76,"memory":65},{"timestamp":1586139960000,"cpu":33,"memory":101},{"timestamp":1586140080000,"cpu":0,"memory":0}]}},{"time":{"start":1586138349318,"deploy":1586138354393,"undeploy":1586139669736,"end":1586139737789},"duration":{"deploy":45446,"execution":1315343,"undeploy":27682,"total":1388471},"status":{"management":"successful","execution":"successful"},"layout":[{"componentId":"9f989b71-aeb9-4cd4-8eed-76051ec3c957","status":"","nbRows":0,"nbRejectedRows":0,"duration":0,"error":""},{"componentId":"cd8ee660-545b-4876-8167-e07c8cd5b429","status":"","nbRows":0,"nbRejectedRows":0,"duration":0,"error":""}],"context":{"executionId":"c6765698-931b-4b12-ad2f-5d9a44d2d9f5","artifact":{"id":"31bb51c6-e879-48e9-a21f-df738cdeb6f2","name":"Business","version":"1.4","type":"pipeline"},"task":{"id":"cd98870c-3d12-4633-959d-1273c56466c0","name":"random-OCA-task-Business","version":"1.0","params":{"param1":"whatever"}},"workspace":{"id":"fcfa35cb-526d-414e-994a-1822d8b62c28","name":"random-OCA"},"environment":{"id":"27fdf8c9-962e-4a89-b614-6be5c4309b40","name":"prod"},"engine":{"id":"6006997c-dcb7-488d-b11b-9864980f1019","name":"random-OCA-engine-0"},"cluster":{"id":"77d7d870-4503-4e47-9f35-3156a1ac7bfd","name":"cluster-random-OCA","runProfile":""},"tags":[],"runType":"plan"},"fingerprint":{"cpu":{"min":7,"max":72,"mean":25},"memory":{"min":44,"max":138,"mean":53},"logs":[{"timestamp":1586138280000,"cpu":0,"memory":0},{"timestamp":1586138400000,"cpu":63,"memory":49},{"timestamp":1586138520000,"cpu":26,"memory":124},{"timestamp":1586138640000,"cpu":11,"memory":66},{"timestamp":1586138760000,"cpu":55,"memory":75},{"timestamp":1586138880000,"cpu":69,"memory":104},{"timestamp":1586139000000,"cpu":68,"memory":129},{"timestamp":1586139120000,"cpu":63,"memory":51},{"timestamp":1586139240000,"cpu":68,"memory":81},{"timestamp":1586139360000,"cpu":17,"memory":65},{"timestamp":1586139480000,"cpu":50,"memory":129},{"timestamp":1586139600000,"cpu":25,"memory":113},{"timestamp":1586139720000,"cpu":0,"memory":0}]}},{"time":{"start":1586145124853,"deploy":1586145140235,"undeploy":1586147656042,"end":1586147719073},"duration":{"deploy":25595,"execution":2515807,"undeploy":52818,"total":2594220},"status":{"management":"successful","execution":"successful"},"layout":[{"componentId":"98360a6c-814f-4de7-8be1-572308c59c07","status":"","nbRows":0,"nbRejectedRows":0,"duration":0,"error":""},{"componentId":"deb565c5-7c9f-420d-828b-7dc5e2fe57ad","status":"","nbRows":0,"nbRejectedRows":0,"duration":0,"error":""}],"context":{"executionId":"7eaf5fb6-247c-4f76-a69d-1a8b3d34ed79","artifact":{"id":"6bf4d0a5-8e3c-4726-99be-72dd20e374e9","name":"Replication","version":"1.11","type":"pipeline"},"task":{"id":"d9869e24-f7b9-4d9b-9f52-ae6f1e623245","name":"random-OCA-task-Replication","version":"1.0","params":{"param1":"whatever"}},"workspace":{"id":"fcfa35cb-526d-414e-994a-1822d8b62c28","name":"random-OCA"},"environment":{"id":"27fdf8c9-962e-4a89-b614-6be5c4309b40","name":"prod"},"engine":{"id":"6006997c-dcb7-488d-b11b-9864980f1019","name":"random-OCA-engine-0"},"cluster":{"id":"77d7d870-4503-4e47-9f35-3156a1ac7bfd","name":"cluster-random-OCA","runProfile":""},"tags":[],"runType":"scheduled"},"fingerprint":{"cpu":{"min":14,"max":72,"mean":27},"memory":{"min":36,"max":225,"mean":95},"logs":[{"timestamp":1586145120000,"cpu":0,"memory":0},{"timestamp":1586145240000,"cpu":20,"memory":80},{"timestamp":1586145360000,"cpu":64,"memory":140},{"timestamp":1586145480000,"cpu":22,"memory":78},{"timestamp":1586145600000,"cpu":33,"memory":165},{"timestamp":1586145720000,"cpu":61,"memory":133},{"timestamp":1586145840000,"cpu":42,"memory":54},{"timestamp":1586145960000,"cpu":68,"memory":219},{"timestamp":1586146080000,"cpu":16,"memory":129},{"timestamp":1586146200000,"cpu":62,"memory":42},{"timestamp":1586146320000,"cpu":15,"memory":140},{"timestamp":1586146440000,"cpu":22,"memory":115},{"timestamp":1586146560000,"cpu":66,"memory":93},{"timestamp":1586146680000,"cpu":60,"memory":42},{"timestamp":1586146800000,"cpu":35,"memory":80},{"timestamp":1586146920000,"cpu":40,"memory":203},{"timestamp":1586147040000,"cpu":25,"memory":202},{"timestamp":1586147160000,"cpu":23,"memory":127},{"timestamp":1586147280000,"cpu":61,"memory":75},{"timestamp":1586147400000,"cpu":29,"memory":144},{"timestamp":1586147520000,"cpu":22,"memory":126},{"timestamp":1586147640000,"cpu":0,"memory":0}]}},{"time":{"start":1586166672079,"deploy":1586166730237,"undeploy":1586170652818,"end":1586170647800},"duration":{"deploy":26920,"execution":3922581,"undeploy":26220,"total":3975721},"status":{"management":"successful","execution":"abort"},"layout":[{"componentId":"677dc32f-9a39-4bee-96e2-eaf9303ed01f","status":"","nbRows":0,"nbRejectedRows":0,"duration":0,"error":""},{"componentId":"4e79cd39-bf68-4500-bd6f-bfffc1cb9764","status":"","nbRows":0,"nbRejectedRows":0,"duration":0,"error":""}],"context":{"executionId":"9fd134d4-008c-4551-a063-8ee2cce767d6","artifact":{"id":"31bb51c6-e879-48e9-a21f-df738cdeb6f2","name":"Business","version":"1.4","type":"pipeline"},"task":{"id":"cd98870c-3d12-4633-959d-1273c56466c0","name":"random-OCA-task-Business","version":"1.0","params":{"param1":"whatever"}},"workspace":{"id":"fcfa35cb-526d-414e-994a-1822d8b62c28","name":"random-OCA"},"environment":{"id":"27fdf8c9-962e-4a89-b614-6be5c4309b40","name":"prod"},"engine":{"id":"6006997c-dcb7-488d-b11b-9864980f1019","name":"random-OCA-engine-0"},"cluster":{"id":"77d7d870-4503-4e47-9f35-3156a1ac7bfd","name":"cluster-random-OCA","runProfile":""},"tags":[],"runType":"manual"},"fingerprint":{"cpu":{"min":0,"max":100,"mean":32},"memory":{"min":40,"max":129,"mean":94},"logs":[{"timestamp":1586166600000,"cpu":0,"memory":0},{"timestamp":1586166720000,"cpu":83,"memory":100},{"timestamp":1586166840000,"cpu":24,"memory":96},{"timestamp":1586166960000,"cpu":42,"memory":42},{"timestamp":1586167080000,"cpu":45,"memory":114},{"timestamp":1586167200000,"cpu":78,"memory":93},{"timestamp":1586167320000,"cpu":63,"memory":43},{"timestamp":1586167440000,"cpu":50,"memory":82},{"timestamp":1586167560000,"cpu":85,"memory":113},{"timestamp":1586167680000,"cpu":37,"memory":70},{"timestamp":1586167800000,"cpu":95,"memory":68},{"timestamp":1586167920000,"cpu":74,"memory":85},{"timestamp":1586168040000,"cpu":25,"memory":79},{"timestamp":1586168160000,"cpu":73,"memory":98},{"timestamp":1586168280000,"cpu":28,"memory":60},{"timestamp":1586168400000,"cpu":46,"memory":102},{"timestamp":1586168520000,"cpu":19,"memory":125},{"timestamp":1586168640000,"cpu":20,"memory":62},{"timestamp":1586168760000,"cpu":21,"memory":111},{"timestamp":1586168880000,"cpu":73,"memory":41},{"timestamp":1586169000000,"cpu":92,"memory":52},{"timestamp":1586169120000,"cpu":6,"memory":43},{"timestamp":1586169240000,"cpu":64,"memory":85},{"timestamp":1586169360000,"cpu":13,"memory":110},{"timestamp":1586169480000,"cpu":36,"memory":65},{"timestamp":1586169600000,"cpu":78,"memory":52},{"timestamp":1586169720000,"cpu":13,"memory":41},{"timestamp":1586169840000,"cpu":79,"memory":101},{"timestamp":1586169960000,"cpu":8,"memory":128},{"timestamp":1586170080000,"cpu":91,"memory":57},{"timestamp":1586170200000,"cpu":79,"memory":54},{"timestamp":1586170320000,"cpu":56,"memory":50},{"timestamp":1586170440000,"cpu":34,"memory":42},{"timestamp":1586170560000,"cpu":0,"memory":0}]}},{"time":{"start":1586206352610,"end":1586206352610},"duration":{"deploy":0,"execution":0,"undeploy":0,"total":0},"status":{"management":"deploy_failure","execution":""},"layout":[{"componentId":"ecc364b3-3652-4e09-b8c6-bcf8ea26bacc","status":"","nbRows":0,"nbRejectedRows":0,"duration":0,"error":""},{"componentId":"c22d676b-20b9-46f5-943e-f985e824fcc6","status":"","nbRows":0,"nbRejectedRows":0,"duration":0,"error":""}],"context":{"executionId":"4cc7ef3b-6108-4947-8520-c2ab5bd4c7bf","artifact":{"id":"ca71143f-56e4-4d22-a4bc-aaf6878fb618","name":"Demo","version":"1.12","type":"pipeline"},"task":{"id":"5ddee1b1-dca4-4999-a0f7-f80f804cfd71","name":"random-OCA-task-Demo","version":"1.0","params":{"param1":"whatever"}},"workspace":{"id":"fcfa35cb-526d-414e-994a-1822d8b62c28","name":"random-OCA"},"environment":{"id":"27fdf8c9-962e-4a89-b614-6be5c4309b40","name":"prod"},"engine":{"id":"6006997c-dcb7-488d-b11b-9864980f1019","name":"random-OCA-engine-0"},"cluster":{"id":"77d7d870-4503-4e47-9f35-3156a1ac7bfd","name":"cluster-random-OCA","runProfile":""},"tags":[],"runType":"webhook"},"retries":[{"engine":{"id":"6006997c-dcb7-488d-b11b-9864980f1019","name":"random-OCA-engine-0"},"time":1586205452610},{"engine":{"id":"6006997c-dcb7-488d-b11b-9864980f1019","name":"random-OCA-engine-0"},"time":1586205752610},{"engine":{"id":"6006997c-dcb7-488d-b11b-9864980f1019","name":"random-OCA-engine-0"},"time":1586206052610},{"engine":{"id":"6006997c-dcb7-488d-b11b-9864980f1019","name":"random-OCA-engine-0"},"time":1586206352610}],"fingerprint":{"cpu":{"min":9,"max":72,"mean":47},"memory":{"min":27,"max":118,"mean":94},"logs":[{"timestamp":1586206320000,"cpu":0,"memory":0},{"timestamp":1586206320000,"cpu":0,"memory":0}]}},{"time":{"start":1586157235847,"deploy":1586157239434,"undeploy":1586158639021,"end":1586158685884},"duration":{"deploy":28094,"execution":1399587,"undeploy":22356,"total":1450037},"status":{"management":"successful","execution":"successful"},"layout":[{"componentId":"fbdb6612-6ff3-473e-8834-42e69084cb9e","status":"","nbRows":0,"nbRejectedRows":0,"duration":0,"error":""},{"componentId":"b6ae1e7a-6080-4079-8916-9eccb9c236fc","status":"","nbRows":0,"nbRejectedRows":0,"duration":0,"error":""}],"context":{"executionId":"bda92b29-9dd9-4d35-80b1-461c680c94ee","artifact":{"id":"6bf4d0a5-8e3c-4726-99be-72dd20e374e9","name":"Replication","version":"1.11","type":"pipeline"},"task":{"id":"d9869e24-f7b9-4d9b-9f52-ae6f1e623245","name":"random-OCA-task-Replication","version":"1.0","params":{"param1":"whatever"}},"workspace":{"id":"fcfa35cb-526d-414e-994a-1822d8b62c28","name":"random-OCA"},"environment":{"id":"27fdf8c9-962e-4a89-b614-6be5c4309b40","name":"prod"},"engine":{"id":"6006997c-dcb7-488d-b11b-9864980f1019","name":"random-OCA-engine-0"},"cluster":{"id":"77d7d870-4503-4e47-9f35-3156a1ac7bfd","name":"cluster-random-OCA","runProfile":""},"tags":[],"runType":"webhook"},"fingerprint":{"cpu":{"min":17,"max":85,"mean":55},"memory":{"min":44,"max":246,"mean":56},"logs":[{"timestamp":1586157120000,"cpu":0,"memory":0},{"timestamp":1586157240000,"cpu":36,"memory":162},{"timestamp":1586157360000,"cpu":27,"memory":46},{"timestamp":1586157480000,"cpu":25,"memory":169},{"timestamp":1586157600000,"cpu":74,"memory":47},{"timestamp":1586157720000,"cpu":45,"memory":99},{"timestamp":1586157840000,"cpu":55,"memory":66},{"timestamp":1586157960000,"cpu":73,"memory":170},{"timestamp":1586158080000,"cpu":81,"memory":176},{"timestamp":1586158200000,"cpu":51,"memory":93},{"timestamp":1586158320000,"cpu":49,"memory":175},{"timestamp":1586158440000,"cpu":58,"memory":96},{"timestamp":1586158560000,"cpu":59,"memory":167},{"timestamp":1586158680000,"cpu":0,"memory":0}]}},{"time":{"start":1586171944375,"deploy":1586171953571,"undeploy":1586172265471,"end":1586172319248},"duration":{"deploy":49629,"execution":311900,"undeploy":13344,"total":374873},"status":{"management":"successful","execution":"successful"},"layout":[{"componentId":"5b43eef2-1f9c-4619-9c6c-f09d9c1aee06","status":"","nbRows":0,"nbRejectedRows":0,"duration":0,"error":""},{"componentId":"cd64c3f8-95c3-4cfa-a280-eea8c4388ffe","status":"","nbRows":0,"nbRejectedRows":0,"duration":0,"error":""}],"context":{"executionId":"a46c9a52-ba2c-457b-b006-29af09ec951c","artifact":{"id":"31bb51c6-e879-48e9-a21f-df738cdeb6f2","name":"Business","version":"1.4","type":"pipeline"},"task":{"id":"cd98870c-3d12-4633-959d-1273c56466c0","name":"random-OCA-task-Business","version":"1.0","params":{"param1":"whatever"}},"workspace":{"id":"fcfa35cb-526d-414e-994a-1822d8b62c28","name":"random-OCA"},"environment":{"id":"27fdf8c9-962e-4a89-b614-6be5c4309b40","name":"prod"},"engine":{"id":"6006997c-dcb7-488d-b11b-9864980f1019","name":"random-OCA-engine-0"},"cluster":{"id":"77d7d870-4503-4e47-9f35-3156a1ac7bfd","name":"cluster-random-OCA","runProfile":""},"tags":[],"runType":"manual"},"fingerprint":{"cpu":{"min":0,"max":75,"mean":67},"memory":{"min":12,"max":110,"mean":99},"logs":[{"timestamp":1586171880000,"cpu":0,"memory":0},{"timestamp":1586172000000,"cpu":45,"memory":39},{"timestamp":1586172120000,"cpu":38,"memory":109},{"timestamp":1586172240000,"cpu":0,"memory":0}]}},{"time":{"start":1586166422439,"end":1586166422439},"duration":{"deploy":0,"execution":0,"undeploy":0,"total":0},"status":{"management":"deploy_failure","execution":""},"layout":[{"componentId":"bf465ff2-906b-402c-b9d4-28714dfbff6e","status":"","nbRows":0,"nbRejectedRows":0,"duration":0,"error":""},{"componentId":"d7d4317d-403f-497d-804b-84c88009248d","status":"","nbRows":0,"nbRejectedRows":0,"duration":0,"error":""}],"context":{"executionId":"bc429262-0577-4e31-8161-9c96f22ce29f","artifact":{"id":"31bb51c6-e879-48e9-a21f-df738cdeb6f2","name":"Business","version":"1.4","type":"pipeline"},"task":{"id":"cd98870c-3d12-4633-959d-1273c56466c0","name":"random-OCA-task-Business","version":"1.0","params":{"param1":"whatever"}},"workspace":{"id":"fcfa35cb-526d-414e-994a-1822d8b62c28","name":"random-OCA"},"environment":{"id":"27fdf8c9-962e-4a89-b614-6be5c4309b40","name":"prod"},"engine":{"id":"6006997c-dcb7-488d-b11b-9864980f1019","name":"random-OCA-engine-0"},"cluster":{"id":"77d7d870-4503-4e47-9f35-3156a1ac7bfd","name":"cluster-random-OCA","runProfile":""},"tags":[],"runType":"manual"},"retries":[{"engine":{"id":"6006997c-dcb7-488d-b11b-9864980f1019","name":"random-OCA-engine-0"},"time":1586165522439},{"engine":{"id":"6006997c-dcb7-488d-b11b-9864980f1019","name":"random-OCA-engine-0"},"time":1586165822439},{"engine":{"id":"6006997c-dcb7-488d-b11b-9864980f1019","name":"random-OCA-engine-0"},"time":1586166122439},{"engine":{"id":"6006997c-dcb7-488d-b11b-9864980f1019","name":"random-OCA-engine-0"},"time":1586166422439}],"fingerprint":{"cpu":{"min":6,"max":91,"mean":41},"memory":{"min":17,"max":227,"mean":77},"logs":[{"timestamp":1586166360000,"cpu":0,"memory":0},{"timestamp":1586166360000,"cpu":0,"memory":0}]}},{"time":{"start":1586201862140,"deploy":1586201905381,"undeploy":1586202211381,"end":1586202256203},"duration":{"deploy":40654,"execution":306000,"undeploy":47409,"total":394063},"status":{"management":"undeploy_failure","execution":"successful"},"layout":[{"componentId":"cece2dc7-457b-4947-a493-f4ef7468c5fb","status":"","nbRows":0,"nbRejectedRows":0,"duration":0,"error":""},{"componentId":"21da202a-45ef-4d20-a31b-eda9142ad6b6","status":"","nbRows":0,"nbRejectedRows":0,"duration":0,"error":""}],"context":{"executionId":"96c81d23-b847-4f43-ba58-7f2bb79eee43","artifact":{"id":"31bb51c6-e879-48e9-a21f-df738cdeb6f2","name":"Business","version":"1.4","type":"pipeline"},"task":{"id":"cd98870c-3d12-4633-959d-1273c56466c0","name":"random-OCA-task-Business","version":"1.0","params":{"param1":"whatever"}},"workspace":{"id":"fcfa35cb-526d-414e-994a-1822d8b62c28","name":"random-OCA"},"environment":{"id":"27fdf8c9-962e-4a89-b614-6be5c4309b40","name":"prod"},"engine":{"id":"6006997c-dcb7-488d-b11b-9864980f1019","name":"random-OCA-engine-0"},"cluster":{"id":"77d7d870-4503-4e47-9f35-3156a1ac7bfd","name":"cluster-random-OCA","runProfile":""},"tags":[],"runType":"plan"},"fingerprint":{"cpu":{"min":18,"max":79,"mean":23},"memory":{"min":27,"max":110,"mean":95},"logs":[{"timestamp":1586201760000,"cpu":0,"memory":0},{"timestamp":1586201880000,"cpu":64,"memory":89},{"timestamp":1586202000000,"cpu":24,"memory":106},{"timestamp":1586202120000,"cpu":51,"memory":54},{"timestamp":1586202240000,"cpu":0,"memory":0}]}},{"time":{"start":1586202586182,"deploy":1586202605546,"end":1586202603724},"duration":{"deploy":17542,"execution":0,"undeploy":0,"total":17542},"status":{"management":"deploy_failure","execution":""},"layout":[{"componentId":"aa144f7b-98ca-402f-bf53-5383c1571650","status":"","nbRows":0,"nbRejectedRows":0,"duration":0,"error":""},{"componentId":"e2608ffc-68ed-4276-a458-241b1155a7f3","status":"","nbRows":0,"nbRejectedRows":0,"duration":0,"error":""}],"context":{"executionId":"44510253-8177-448e-a6ba-01833ca9f514","artifact":{"id":"6bf4d0a5-8e3c-4726-99be-72dd20e374e9","name":"Replication","version":"1.11","type":"pipeline"},"task":{"id":"d9869e24-f7b9-4d9b-9f52-ae6f1e623245","name":"random-OCA-task-Replication","version":"1.0","params":{"param1":"whatever"}},"workspace":{"id":"fcfa35cb-526d-414e-994a-1822d8b62c28","name":"random-OCA"},"environment":{"id":"27fdf8c9-962e-4a89-b614-6be5c4309b40","name":"prod"},"engine":{"id":"6006997c-dcb7-488d-b11b-9864980f1019","name":"random-OCA-engine-0"},"cluster":{"id":"77d7d870-4503-4e47-9f35-3156a1ac7bfd","name":"cluster-random-OCA","runProfile":""},"tags":[],"runType":"webhook"},"fingerprint":{"cpu":{"min":18,"max":73,"mean":31},"memory":{"min":6,"max":133,"mean":98},"logs":[{"timestamp":1586202480000,"cpu":0,"memory":0},{"timestamp":1586202600000,"cpu":0,"memory":0}]}},{"time":{"start":1586124744421,"end":1586124744421},"duration":{"deploy":0,"execution":0,"undeploy":0,"total":0},"status":{"management":"deploy_failure","execution":""},"layout":[{"componentId":"de6c1844-e402-48ab-81f0-e1d5ed2e94e5","status":"","nbRows":0,"nbRejectedRows":0,"duration":0,"error":""},{"componentId":"5daf971c-ecf7-40f0-9930-a54a59d85aa7","status":"","nbRows":0,"nbRejectedRows":0,"duration":0,"error":""}],"context":{"executionId":"538e3d7f-24b5-44a4-877e-9e83231936aa","artifact":{"id":"6bf4d0a5-8e3c-4726-99be-72dd20e374e9","name":"Replication","version":"1.11","type":"pipeline"},"task":{"id":"d9869e24-f7b9-4d9b-9f52-ae6f1e623245","name":"random-OCA-task-Replication","version":"1.0","params":{"param1":"whatever"}},"workspace":{"id":"fcfa35cb-526d-414e-994a-1822d8b62c28","name":"random-OCA"},"environment":{"id":"27fdf8c9-962e-4a89-b614-6be5c4309b40","name":"prod"},"engine":{"id":"6006997c-dcb7-488d-b11b-9864980f1019","name":"random-OCA-engine-0"},"cluster":{"id":"77d7d870-4503-4e47-9f35-3156a1ac7bfd","name":"cluster-random-OCA","runProfile":""},"tags":[],"runType":"plan"},"retries":[{"engine":{"id":"6006997c-dcb7-488d-b11b-9864980f1019","name":"random-OCA-engine-0"},"time":1586123844421},{"engine":{"id":"6006997c-dcb7-488d-b11b-9864980f1019","name":"random-OCA-engine-0"},"time":1586124144421},{"engine":{"id":"6006997c-dcb7-488d-b11b-9864980f1019","name":"random-OCA-engine-0"},"time":1586124444421},{"engine":{"id":"6006997c-dcb7-488d-b11b-9864980f1019","name":"random-OCA-engine-0"},"time":1586124744421}],"fingerprint":{"cpu":{"min":12,"max":89,"mean":32},"memory":{"min":44,"max":195,"mean":97},"logs":[{"timestamp":1586124720000,"cpu":0,"memory":0},{"timestamp":1586124720000,"cpu":0,"memory":0}]}},{"time":{"start":1586138882498,"end":1586138882498},"duration":{"deploy":0,"execution":0,"undeploy":0,"total":0},"status":{"management":"deploy_failure","execution":""},"layout":[{"componentId":"2f5be4ec-ef94-46f4-a06e-d2fe7fde0c6e","status":"","nbRows":0,"nbRejectedRows":0,"duration":0,"error":""},{"componentId":"751f3b53-ed49-4742-970c-a0205f7fd47b","status":"","nbRows":0,"nbRejectedRows":0,"duration":0,"error":""}],"context":{"executionId":"c3b17ff6-cd39-483a-ad7b-2bdf54079d09","artifact":{"id":"ca71143f-56e4-4d22-a4bc-aaf6878fb618","name":"Demo","version":"1.12","type":"pipeline"},"task":{"id":"5ddee1b1-dca4-4999-a0f7-f80f804cfd71","name":"random-OCA-task-Demo","version":"1.0","params":{"param1":"whatever"}},"workspace":{"id":"fcfa35cb-526d-414e-994a-1822d8b62c28","name":"random-OCA"},"environment":{"id":"27fdf8c9-962e-4a89-b614-6be5c4309b40","name":"prod"},"engine":{"id":"6006997c-dcb7-488d-b11b-9864980f1019","name":"random-OCA-engine-0"},"cluster":{"id":"77d7d870-4503-4e47-9f35-3156a1ac7bfd","name":"cluster-random-OCA","runProfile":""},"tags":[],"runType":"webhook"},"retries":[{"engine":{"id":"6006997c-dcb7-488d-b11b-9864980f1019","name":"random-OCA-engine-0"},"time":1586137982498},{"engine":{"id":"6006997c-dcb7-488d-b11b-9864980f1019","name":"random-OCA-engine-0"},"time":1586138282498},{"engine":{"id":"6006997c-dcb7-488d-b11b-9864980f1019","name":"random-OCA-engine-0"},"time":1586138582498},{"engine":{"id":"6006997c-dcb7-488d-b11b-9864980f1019","name":"random-OCA-engine-0"},"time":1586138882498}],"fingerprint":{"cpu":{"min":6,"max":74,"mean":30},"memory":{"min":48,"max":237,"mean":77},"logs":[{"timestamp":1586138880000,"cpu":0,"memory":0},{"timestamp":1586138880000,"cpu":0,"memory":0}]}},{"time":{"start":1586195892680,"deploy":1586195929030,"undeploy":1586198710301,"end":1586198715666},"duration":{"deploy":24867,"execution":2781271,"undeploy":16848,"total":2822986},"status":{"management":"successful","execution":"successful"},"layout":[{"componentId":"68c0acc6-4e29-4beb-95f4-c9e780a554ef","status":"","nbRows":0,"nbRejectedRows":0,"duration":0,"error":""},{"componentId":"0378096f-fc3a-4caf-9279-0c6338e57a58","status":"","nbRows":0,"nbRejectedRows":0,"duration":0,"error":""}],"context":{"executionId":"d6ee88b1-be11-48c0-8db1-95784f31577f","artifact":{"id":"31bb51c6-e879-48e9-a21f-df738cdeb6f2","name":"Business","version":"1.4","type":"pipeline"},"task":{"id":"cd98870c-3d12-4633-959d-1273c56466c0","name":"random-OCA-task-Business","version":"1.0","params":{"param1":"whatever"}},"workspace":{"id":"fcfa35cb-526d-414e-994a-1822d8b62c28","name":"random-OCA"},"environment":{"id":"27fdf8c9-962e-4a89-b614-6be5c4309b40","name":"prod"},"engine":{"id":"6006997c-dcb7-488d-b11b-9864980f1019","name":"random-OCA-engine-0"},"cluster":{"id":"77d7d870-4503-4e47-9f35-3156a1ac7bfd","name":"cluster-random-OCA","runProfile":""},"tags":[],"runType":"manual"},"fingerprint":{"cpu":{"min":17,"max":73,"mean":44},"memory":{"min":40,"max":166,"mean":86},"logs":[{"timestamp":1586195880000,"cpu":0,"memory":0},{"timestamp":1586196000000,"cpu":52,"memory":54},{"timestamp":1586196120000,"cpu":29,"memory":134},{"timestamp":1586196240000,"cpu":40,"memory":164},{"timestamp":1586196360000,"cpu":70,"memory":107},{"timestamp":1586196480000,"cpu":51,"memory":45},{"timestamp":1586196600000,"cpu":70,"memory":102},{"timestamp":1586196720000,"cpu":53,"memory":109},{"timestamp":1586196840000,"cpu":43,"memory":88},{"timestamp":1586196960000,"cpu":56,"memory":104},{"timestamp":1586197080000,"cpu":44,"memory":134},{"timestamp":1586197200000,"cpu":62,"memory":135},{"timestamp":1586197320000,"cpu":35,"memory":146},{"timestamp":1586197440000,"cpu":21,"memory":101},{"timestamp":1586197560000,"cpu":19,"memory":129},{"timestamp":1586197680000,"cpu":34,"memory":111},{"timestamp":1586197800000,"cpu":40,"memory":72},{"timestamp":1586197920000,"cpu":67,"memory":150},{"timestamp":1586198040000,"cpu":45,"memory":59},{"timestamp":1586198160000,"cpu":59,"memory":150},{"timestamp":1586198280000,"cpu":68,"memory":68},{"timestamp":1586198400000,"cpu":72,"memory":115},{"timestamp":1586198520000,"cpu":29,"memory":135},{"timestamp":1586198640000,"cpu":0,"memory":0}]}},{"time":{"start":1586184455702,"deploy":1586184468875,"undeploy":1586186465697,"end":1586186463723},"duration":{"deploy":8667,"execution":1996822,"undeploy":2532,"total":2008021},"status":{"management":"successful","execution":"successful"},"layout":[{"componentId":"065cded1-af3b-4c11-be94-9432ee501462","status":"","nbRows":0,"nbRejectedRows":0,"duration":0,"error":""},{"componentId":"23ef9ecb-2c0c-4086-bf16-de94680a25c6","status":"","nbRows":0,"nbRejectedRows":0,"duration":0,"error":""}],"context":{"executionId":"b9b7ffcc-6512-40e7-a6ef-e84f9dc731c0","artifact":{"id":"31bb51c6-e879-48e9-a21f-df738cdeb6f2","name":"Business","version":"1.4","type":"pipeline"},"task":{"id":"cd98870c-3d12-4633-959d-1273c56466c0","name":"random-OCA-task-Business","version":"1.0","params":{"param1":"whatever"}},"workspace":{"id":"fcfa35cb-526d-414e-994a-1822d8b62c28","name":"random-OCA"},"environment":{"id":"27fdf8c9-962e-4a89-b614-6be5c4309b40","name":"prod"},"engine":{"id":"6006997c-dcb7-488d-b11b-9864980f1019","name":"random-OCA-engine-0"},"cluster":{"id":"77d7d870-4503-4e47-9f35-3156a1ac7bfd","name":"cluster-random-OCA","runProfile":""},"tags":[],"runType":"api"},"fingerprint":{"cpu":{"min":18,"max":77,"mean":36},"memory":{"min":12,"max":217,"mean":86},"logs":[{"timestamp":1586184360000,"cpu":0,"memory":0},{"timestamp":1586184480000,"cpu":43,"memory":195},{"timestamp":1586184600000,"cpu":28,"memory":148},{"timestamp":1586184720000,"cpu":73,"memory":164},{"timestamp":1586184840000,"cpu":52,"memory":72},{"timestamp":1586184960000,"cpu":46,"memory":193},{"timestamp":1586185080000,"cpu":26,"memory":13},{"timestamp":1586185200000,"cpu":39,"memory":172},{"timestamp":1586185320000,"cpu":23,"memory":168},{"timestamp":1586185440000,"cpu":46,"memory":185},{"timestamp":1586185560000,"cpu":64,"memory":162},{"timestamp":1586185680000,"cpu":27,"memory":187},{"timestamp":1586185800000,"cpu":74,"memory":23},{"timestamp":1586185920000,"cpu":35,"memory":87},{"timestamp":1586186040000,"cpu":60,"memory":157},{"timestamp":1586186160000,"cpu":29,"memory":69},{"timestamp":1586186280000,"cpu":30,"memory":44},{"timestamp":1586186400000,"cpu":0,"memory":0}]}},{"time":{"start":1586192832927,"deploy":1586192843974,"undeploy":1586195615982,"end":1586195667429},"duration":{"deploy":10760,"execution":2772008,"undeploy":51734,"total":2834502},"status":{"management":"successful","execution":"successful"},"layout":[{"componentId":"d1deb7b5-4129-4379-8c24-1662e9319e1f","status":"","nbRows":0,"nbRejectedRows":0,"duration":0,"error":""},{"componentId":"ac716db6-4a19-4bf1-b04b-fad5db43fbe0","status":"","nbRows":0,"nbRejectedRows":0,"duration":0,"error":""}],"context":{"executionId":"0dda9d6f-83ea-431f-8a50-265c3dc829b5","artifact":{"id":"6bf4d0a5-8e3c-4726-99be-72dd20e374e9","name":"Replication","version":"1.11","type":"pipeline"},"task":{"id":"d9869e24-f7b9-4d9b-9f52-ae6f1e623245","name":"random-OCA-task-Replication","version":"1.0","params":{"param1":"whatever"}},"workspace":{"id":"fcfa35cb-526d-414e-994a-1822d8b62c28","name":"random-OCA"},"environment":{"id":"27fdf8c9-962e-4a89-b614-6be5c4309b40","name":"prod"},"engine":{"id":"6006997c-dcb7-488d-b11b-9864980f1019","name":"random-OCA-engine-0"},"cluster":{"id":"77d7d870-4503-4e47-9f35-3156a1ac7bfd","name":"cluster-random-OCA","runProfile":""},"tags":[],"runType":"webhook"},"fingerprint":{"cpu":{"min":5,"max":87,"mean":26},"memory":{"min":18,"max":199,"mean":75},"logs":[{"timestamp":1586192760000,"cpu":0,"memory":0},{"timestamp":1586192880000,"cpu":24,"memory":90},{"timestamp":1586193000000,"cpu":52,"memory":161},{"timestamp":1586193120000,"cpu":56,"memory":57},{"timestamp":1586193240000,"cpu":73,"memory":137},{"timestamp":1586193360000,"cpu":67,"memory":91},{"timestamp":1586193480000,"cpu":27,"memory":191},{"timestamp":1586193600000,"cpu":24,"memory":76},{"timestamp":1586193720000,"cpu":10,"memory":97},{"timestamp":1586193840000,"cpu":23,"memory":54},{"timestamp":1586193960000,"cpu":77,"memory":183},{"timestamp":1586194080000,"cpu":29,"memory":109},{"timestamp":1586194200000,"cpu":59,"memory":182},{"timestamp":1586194320000,"cpu":58,"memory":27},{"timestamp":1586194440000,"cpu":28,"memory":168},{"timestamp":1586194560000,"cpu":12,"memory":175},{"timestamp":1586194680000,"cpu":9,"memory":96},{"timestamp":1586194800000,"cpu":33,"memory":125},{"timestamp":1586194920000,"cpu":65,"memory":113},{"timestamp":1586195040000,"cpu":40,"memory":146},{"timestamp":1586195160000,"cpu":5,"memory":146},{"timestamp":1586195280000,"cpu":21,"memory":87},{"timestamp":1586195400000,"cpu":50,"memory":173},{"timestamp":1586195520000,"cpu":85,"memory":125},{"timestamp":1586195640000,"cpu":0,"memory":0}]}},{"time":{"start":1586142571175,"end":1586142571175},"duration":{"deploy":0,"execution":0,"undeploy":0,"total":0},"status":{"management":"deploy_failure","execution":""},"layout":[{"componentId":"f3e37e58-8219-4ca4-9654-71cdbbf1d0d3","status":"","nbRows":0,"nbRejectedRows":0,"duration":0,"error":""},{"componentId":"1608c239-7a97-4592-a479-b55def41f1c6","status":"","nbRows":0,"nbRejectedRows":0,"duration":0,"error":""}],"context":{"executionId":"8c8d3424-d035-422c-be2c-ed28fd11157f","artifact":{"id":"ca71143f-56e4-4d22-a4bc-aaf6878fb618","name":"Demo","version":"1.12","type":"pipeline"},"task":{"id":"5ddee1b1-dca4-4999-a0f7-f80f804cfd71","name":"random-OCA-task-Demo","version":"1.0","params":{"param1":"whatever"}},"workspace":{"id":"fcfa35cb-526d-414e-994a-1822d8b62c28","name":"random-OCA"},"environment":{"id":"27fdf8c9-962e-4a89-b614-6be5c4309b40","name":"prod"},"engine":{"id":"6006997c-dcb7-488d-b11b-9864980f1019","name":"random-OCA-engine-0"},"cluster":{"id":"77d7d870-4503-4e47-9f35-3156a1ac7bfd","name":"cluster-random-OCA","runProfile":""},"tags":[],"runType":"plan"},"retries":[{"engine":{"id":"6006997c-dcb7-488d-b11b-9864980f1019","name":"random-OCA-engine-0"},"time":1586141671175},{"engine":{"id":"6006997c-dcb7-488d-b11b-9864980f1019","name":"random-OCA-engine-0"},"time":1586141971175},{"engine":{"id":"6006997c-dcb7-488d-b11b-9864980f1019","name":"random-OCA-engine-0"},"time":1586142271175},{"engine":{"id":"6006997c-dcb7-488d-b11b-9864980f1019","name":"random-OCA-engine-0"},"time":1586142571175}],"fingerprint":{"cpu":{"min":9,"max":79,"mean":45},"memory":{"min":37,"max":125,"mean":87},"logs":[{"timestamp":1586142480000,"cpu":0,"memory":0},{"timestamp":1586142480000,"cpu":0,"memory":0}]}},{"time":{"start":1586167216821,"deploy":1586167253407,"undeploy":1586167763128,"end":1586167788781},"duration":{"deploy":51552,"execution":509721,"undeploy":10687,"total":571960},"status":{"management":"successful","execution":"successful"},"layout":[{"componentId":"e008bb97-35b1-4a0f-9c15-29b773cc986c","status":"","nbRows":0,"nbRejectedRows":0,"duration":0,"error":""},{"componentId":"0d991b90-c1b5-4d49-bf41-f655459134ee","status":"","nbRows":0,"nbRejectedRows":0,"duration":0,"error":""}],"context":{"executionId":"3b60e8c9-e51d-4fd9-8b95-a2bb6b355e47","artifact":{"id":"6bf4d0a5-8e3c-4726-99be-72dd20e374e9","name":"Replication","version":"1.11","type":"pipeline"},"task":{"id":"d9869e24-f7b9-4d9b-9f52-ae6f1e623245","name":"random-OCA-task-Replication","version":"1.0","params":{"param1":"whatever"}},"workspace":{"id":"fcfa35cb-526d-414e-994a-1822d8b62c28","name":"random-OCA"},"environment":{"id":"27fdf8c9-962e-4a89-b614-6be5c4309b40","name":"prod"},"engine":{"id":"6006997c-dcb7-488d-b11b-9864980f1019","name":"random-OCA-engine-0"},"cluster":{"id":"77d7d870-4503-4e47-9f35-3156a1ac7bfd","name":"cluster-random-OCA","runProfile":""},"tags":[],"runType":"scheduled"},"fingerprint":{"cpu":{"min":11,"max":91,"mean":53},"memory":{"min":38,"max":160,"mean":58},"logs":[{"timestamp":1586167200000,"cpu":0,"memory":0},{"timestamp":1586167320000,"cpu":53,"memory":71},{"timestamp":1586167440000,"cpu":53,"memory":88},{"timestamp":1586167560000,"cpu":56,"memory":116},{"timestamp":1586167680000,"cpu":0,"memory":0}]}},{"time":{"start":1586153583258,"deploy":1586153611543,"end":1586153641957},"duration":{"deploy":58699,"execution":0,"undeploy":0,"total":58699},"status":{"management":"deploy_failure","execution":""},"layout":[{"componentId":"8c4d587b-98bf-4798-9484-4e220e81ab1a","status":"","nbRows":0,"nbRejectedRows":0,"duration":0,"error":""},{"componentId":"c047174b-efb6-45bf-9e34-2c1b72e34707","status":"","nbRows":0,"nbRejectedRows":0,"duration":0,"error":""}],"context":{"executionId":"dd3d0076-1cd9-4bb1-8397-8efff57c0602","artifact":{"id":"31bb51c6-e879-48e9-a21f-df738cdeb6f2","name":"Business","version":"1.4","type":"pipeline"},"task":{"id":"cd98870c-3d12-4633-959d-1273c56466c0","name":"random-OCA-task-Business","version":"1.0","params":{"param1":"whatever"}},"workspace":{"id":"fcfa35cb-526d-414e-994a-1822d8b62c28","name":"random-OCA"},"environment":{"id":"27fdf8c9-962e-4a89-b614-6be5c4309b40","name":"prod"},"engine":{"id":"6006997c-dcb7-488d-b11b-9864980f1019","name":"random-OCA-engine-0"},"cluster":{"id":"77d7d870-4503-4e47-9f35-3156a1ac7bfd","name":"cluster-random-OCA","runProfile":""},"tags":[],"runType":"manual"},"fingerprint":{"cpu":{"min":5,"max":70,"mean":21},"memory":{"min":18,"max":110,"mean":52},"logs":[{"timestamp":1586153520000,"cpu":0,"memory":0},{"timestamp":1586153640000,"cpu":0,"memory":0}]}},{"time":{"start":1586201533529,"deploy":1586201573915,"end":1586201582406},"duration":{"deploy":48877,"execution":0,"undeploy":0,"total":48877},"status":{"management":"deploy_failure","execution":""},"layout":[{"componentId":"a3d2e058-5a86-46b6-bf10-e1ce9c1dbced","status":"","nbRows":0,"nbRejectedRows":0,"duration":0,"error":""},{"componentId":"63051db7-331f-45a3-9488-3dd69f49affb","status":"","nbRows":0,"nbRejectedRows":0,"duration":0,"error":""}],"context":{"executionId":"7be318df-d7a6-4600-805b-c6e6283a5f4a","artifact":{"id":"31bb51c6-e879-48e9-a21f-df738cdeb6f2","name":"Business","version":"1.4","type":"pipeline"},"task":{"id":"cd98870c-3d12-4633-959d-1273c56466c0","name":"random-OCA-task-Business","version":"1.0","params":{"param1":"whatever"}},"workspace":{"id":"fcfa35cb-526d-414e-994a-1822d8b62c28","name":"random-OCA"},"environment":{"id":"27fdf8c9-962e-4a89-b614-6be5c4309b40","name":"prod"},"engine":{"id":"6006997c-dcb7-488d-b11b-9864980f1019","name":"random-OCA-engine-0"},"cluster":{"id":"77d7d870-4503-4e47-9f35-3156a1ac7bfd","name":"cluster-random-OCA","runProfile":""},"tags":[],"runType":"manual"},"fingerprint":{"cpu":{"min":8,"max":71,"mean":65},"memory":{"min":35,"max":201,"mean":95},"logs":[{"timestamp":1586201520000,"cpu":0,"memory":0},{"timestamp":1586201520000,"cpu":0,"memory":0}]}},{"time":{"start":1586182158441,"end":1586182158441},"duration":{"deploy":0,"execution":0,"undeploy":0,"total":0},"status":{"management":"deploy_failure","execution":""},"layout":[{"componentId":"90f8d5a2-8bac-4712-8653-b4e6819166ea","status":"","nbRows":0,"nbRejectedRows":0,"duration":0,"error":""},{"componentId":"86e1e9c0-1450-40af-a9b9-60c2678c9086","status":"","nbRows":0,"nbRejectedRows":0,"duration":0,"error":""}],"context":{"executionId":"69acc94f-b92e-4373-a194-49e1341549db","artifact":{"id":"ca71143f-56e4-4d22-a4bc-aaf6878fb618","name":"Demo","version":"1.12","type":"pipeline"},"task":{"id":"5ddee1b1-dca4-4999-a0f7-f80f804cfd71","name":"random-OCA-task-Demo","version":"1.0","params":{"param1":"whatever"}},"workspace":{"id":"fcfa35cb-526d-414e-994a-1822d8b62c28","name":"random-OCA"},"environment":{"id":"27fdf8c9-962e-4a89-b614-6be5c4309b40","name":"prod"},"engine":{"id":"6006997c-dcb7-488d-b11b-9864980f1019","name":"random-OCA-engine-0"},"cluster":{"id":"77d7d870-4503-4e47-9f35-3156a1ac7bfd","name":"cluster-random-OCA","runProfile":""},"tags":[],"runType":"plan"},"retries":[{"engine":{"id":"6006997c-dcb7-488d-b11b-9864980f1019","name":"random-OCA-engine-0"},"time":1586181258441},{"engine":{"id":"6006997c-dcb7-488d-b11b-9864980f1019","name":"random-OCA-engine-0"},"time":1586181558441},{"engine":{"id":"6006997c-dcb7-488d-b11b-9864980f1019","name":"random-OCA-engine-0"},"time":1586181858441},{"engine":{"id":"6006997c-dcb7-488d-b11b-9864980f1019","name":"random-OCA-engine-0"},"time":1586182158441}],"fingerprint":{"cpu":{"min":13,"max":88,"mean":23},"memory":{"min":23,"max":236,"mean":57},"logs":[{"timestamp":1586182080000,"cpu":0,"memory":0},{"timestamp":1586182080000,"cpu":0,"memory":0}]}},{"time":{"start":1586152657133,"end":1586152657133},"duration":{"deploy":0,"execution":0,"undeploy":0,"total":0},"status":{"management":"deploy_failure","execution":""},"layout":[{"componentId":"c71d4df7-076f-49a9-b421-c9ec68138820","status":"","nbRows":0,"nbRejectedRows":0,"duration":0,"error":""},{"componentId":"2497a8ac-b784-49a4-90b6-4f877a502b5a","status":"","nbRows":0,"nbRejectedRows":0,"duration":0,"error":""}],"context":{"executionId":"7e5ececc-c1a8-4453-9f8b-970dbed3e1ff","artifact":{"id":"31bb51c6-e879-48e9-a21f-df738cdeb6f2","name":"Business","version":"1.4","type":"pipeline"},"task":{"id":"cd98870c-3d12-4633-959d-1273c56466c0","name":"random-OCA-task-Business","version":"1.0","params":{"param1":"whatever"}},"workspace":{"id":"fcfa35cb-526d-414e-994a-1822d8b62c28","name":"random-OCA"},"environment":{"id":"27fdf8c9-962e-4a89-b614-6be5c4309b40","name":"prod"},"engine":{"id":"6006997c-dcb7-488d-b11b-9864980f1019","name":"random-OCA-engine-0"},"cluster":{"id":"77d7d870-4503-4e47-9f35-3156a1ac7bfd","name":"cluster-random-OCA","runProfile":""},"tags":[],"runType":"scheduled"},"retries":[{"engine":{"id":"6006997c-dcb7-488d-b11b-9864980f1019","name":"random-OCA-engine-0"},"time":1586151757133},{"engine":{"id":"6006997c-dcb7-488d-b11b-9864980f1019","name":"random-OCA-engine-0"},"time":1586152057133},{"engine":{"id":"6006997c-dcb7-488d-b11b-9864980f1019","name":"random-OCA-engine-0"},"time":1586152357133},{"engine":{"id":"6006997c-dcb7-488d-b11b-9864980f1019","name":"random-OCA-engine-0"},"time":1586152657133}],"fingerprint":{"cpu":{"min":5,"max":86,"mean":51},"memory":{"min":29,"max":176,"mean":92},"logs":[{"timestamp":1586152560000,"cpu":0,"memory":0},{"timestamp":1586152560000,"cpu":0,"memory":0}]}},{"time":{"start":1586178609733,"deploy":1586178624567,"undeploy":1586181404255,"end":1586181478612},"duration":{"deploy":41424,"execution":2779688,"undeploy":47767,"total":2868879},"status":{"management":"successful","execution":"successful"},"layout":[{"componentId":"90ccffb4-0f48-4af7-8203-0eebd48d1946","status":"","nbRows":0,"nbRejectedRows":0,"duration":0,"error":""},{"componentId":"d237f438-4cc7-4b4f-a326-f1b3903465e0","status":"","nbRows":0,"nbRejectedRows":0,"duration":0,"error":""}],"context":{"executionId":"ccbd9539-7946-43d3-a8a5-073400da15b6","artifact":{"id":"6bf4d0a5-8e3c-4726-99be-72dd20e374e9","name":"Replication","version":"1.11","type":"pipeline"},"task":{"id":"d9869e24-f7b9-4d9b-9f52-ae6f1e623245","name":"random-OCA-task-Replication","version":"1.0","params":{"param1":"whatever"}},"workspace":{"id":"fcfa35cb-526d-414e-994a-1822d8b62c28","name":"random-OCA"},"environment":{"id":"27fdf8c9-962e-4a89-b614-6be5c4309b40","name":"prod"},"engine":{"id":"6006997c-dcb7-488d-b11b-9864980f1019","name":"random-OCA-engine-0"},"cluster":{"id":"77d7d870-4503-4e47-9f35-3156a1ac7bfd","name":"cluster-random-OCA","runProfile":""},"tags":[],"runType":"webhook"},"fingerprint":{"cpu":{"min":6,"max":100,"mean":20},"memory":{"min":15,"max":135,"mean":94},"logs":[{"timestamp":1586178600000,"cpu":0,"memory":0},{"timestamp":1586178720000,"cpu":25,"memory":56},{"timestamp":1586178840000,"cpu":93,"memory":121},{"timestamp":1586178960000,"cpu":25,"memory":119},{"timestamp":1586179080000,"cpu":14,"memory":62},{"timestamp":1586179200000,"cpu":20,"memory":103},{"timestamp":1586179320000,"cpu":26,"memory":22},{"timestamp":1586179440000,"cpu":62,"memory":54},{"timestamp":1586179560000,"cpu":97,"memory":96},{"timestamp":1586179680000,"cpu":67,"memory":105},{"timestamp":1586179800000,"cpu":84,"memory":79},{"timestamp":1586179920000,"cpu":48,"memory":17},{"timestamp":1586180040000,"cpu":69,"memory":73},{"timestamp":1586180160000,"cpu":54,"memory":90},{"timestamp":1586180280000,"cpu":20,"memory":114},{"timestamp":1586180400000,"cpu":95,"memory":135},{"timestamp":1586180520000,"cpu":63,"memory":123},{"timestamp":1586180640000,"cpu":87,"memory":118},{"timestamp":1586180760000,"cpu":48,"memory":28},{"timestamp":1586180880000,"cpu":16,"memory":69},{"timestamp":1586181000000,"cpu":15,"memory":48},{"timestamp":1586181120000,"cpu":27,"memory":109},{"timestamp":1586181240000,"cpu":55,"memory":89},{"timestamp":1586181360000,"cpu":0,"memory":0}]}},{"time":{"start":1586123544372,"deploy":1586123547887,"undeploy":1586125344253,"end":1586125417445},"duration":{"deploy":19855,"execution":1796366,"undeploy":56852,"total":1873073},"status":{"management":"successful","execution":"successful"},"layout":[{"componentId":"ab3638fb-7f0e-43d8-800c-c11bab4844aa","status":"","nbRows":0,"nbRejectedRows":0,"duration":0,"error":""},{"componentId":"105fd45a-0d14-4f40-9d72-09007b6e6379","status":"","nbRows":0,"nbRejectedRows":0,"duration":0,"error":""}],"context":{"executionId":"09707a5b-a01e-4403-8709-fc7600c3f042","artifact":{"id":"ca71143f-56e4-4d22-a4bc-aaf6878fb618","name":"Demo","version":"1.12","type":"pipeline"},"task":{"id":"5ddee1b1-dca4-4999-a0f7-f80f804cfd71","name":"random-OCA-task-Demo","version":"1.0","params":{"param1":"whatever"}},"workspace":{"id":"fcfa35cb-526d-414e-994a-1822d8b62c28","name":"random-OCA"},"environment":{"id":"27fdf8c9-962e-4a89-b614-6be5c4309b40","name":"prod"},"engine":{"id":"6006997c-dcb7-488d-b11b-9864980f1019","name":"random-OCA-engine-0"},"cluster":{"id":"77d7d870-4503-4e47-9f35-3156a1ac7bfd","name":"cluster-random-OCA","runProfile":""},"tags":[],"runType":"webhook"},"fingerprint":{"cpu":{"min":8,"max":99,"mean":38},"memory":{"min":8,"max":176,"mean":71},"logs":[{"timestamp":1586123520000,"cpu":0,"memory":0},{"timestamp":1586123640000,"cpu":95,"memory":21},{"timestamp":1586123760000,"cpu":86,"memory":16},{"timestamp":1586123880000,"cpu":84,"memory":44},{"timestamp":1586124000000,"cpu":83,"memory":149},{"timestamp":1586124120000,"cpu":97,"memory":146},{"timestamp":1586124240000,"cpu":76,"memory":79},{"timestamp":1586124360000,"cpu":53,"memory":79},{"timestamp":1586124480000,"cpu":33,"memory":169},{"timestamp":1586124600000,"cpu":88,"memory":114},{"timestamp":1586124720000,"cpu":91,"memory":39},{"timestamp":1586124840000,"cpu":98,"memory":16},{"timestamp":1586124960000,"cpu":82,"memory":99},{"timestamp":1586125080000,"cpu":21,"memory":63},{"timestamp":1586125200000,"cpu":37,"memory":111},{"timestamp":1586125320000,"cpu":0,"memory":0}]}},{"time":{"start":1586196877035,"end":1586196877035},"duration":{"deploy":0,"execution":0,"undeploy":0,"total":0},"status":{"management":"deploy_failure","execution":""},"layout":[{"componentId":"09701763-b1af-43ee-b81e-755cc25e95e1","status":"","nbRows":0,"nbRejectedRows":0,"duration":0,"error":""},{"componentId":"c3812b87-15da-4389-b3ea-404d8bdfa21b","status":"","nbRows":0,"nbRejectedRows":0,"duration":0,"error":""}],"context":{"executionId":"8540b68b-da40-4762-818a-0c99be1e543e","artifact":{"id":"31bb51c6-e879-48e9-a21f-df738cdeb6f2","name":"Business","version":"1.4","type":"pipeline"},"task":{"id":"cd98870c-3d12-4633-959d-1273c56466c0","name":"random-OCA-task-Business","version":"1.0","params":{"param1":"whatever"}},"workspace":{"id":"fcfa35cb-526d-414e-994a-1822d8b62c28","name":"random-OCA"},"environment":{"id":"27fdf8c9-962e-4a89-b614-6be5c4309b40","name":"prod"},"engine":{"id":"6006997c-dcb7-488d-b11b-9864980f1019","name":"random-OCA-engine-0"},"cluster":{"id":"77d7d870-4503-4e47-9f35-3156a1ac7bfd","name":"cluster-random-OCA","runProfile":""},"tags":[],"runType":"plan"},"retries":[{"engine":{"id":"6006997c-dcb7-488d-b11b-9864980f1019","name":"random-OCA-engine-0"},"time":1586195977035},{"engine":{"id":"6006997c-dcb7-488d-b11b-9864980f1019","name":"random-OCA-engine-0"},"time":1586196277035},{"engine":{"id":"6006997c-dcb7-488d-b11b-9864980f1019","name":"random-OCA-engine-0"},"time":1586196577035},{"engine":{"id":"6006997c-dcb7-488d-b11b-9864980f1019","name":"random-OCA-engine-0"},"time":1586196877035}],"fingerprint":{"cpu":{"min":2,"max":88,"mean":52},"memory":{"min":19,"max":185,"mean":74},"logs":[{"timestamp":1586196840000,"cpu":0,"memory":0},{"timestamp":1586196840000,"cpu":0,"memory":0}]}}]}