{"timeRange":{"start":1585904400000,"end":1585908000000},"engine":"prod-engine-1","executions":[{"time":{"start":1585900800000,"deploy":1585900847493,"undeploy":1585906913559,"end":1585906906987},"duration":{"deploy":40304,"execution":6066066,"undeploy":617,"total":6106987},"status":{"management":"successful","execution":"successful"},"layout":[{"componentId":"8086fb06-621c-4cc5-aa76-d3722a5c85ee","status":"","nbRows":0,"nbRejectedRows":0,"duration":0,"error":""},{"componentId":"0a7d2306-f3f9-4820-9197-1a2b0e403584","status":"","nbRows":0,"nbRejectedRows":0,"duration":0,"error":""}],"context":{"executionId":"a184685e-b378-4763-bffd-b2fe5aaf6fd2","artifact":{"id":"379ad3ef-20c3-486c-95be-ef76672c1082","name":"Business","version":"0.14","type":"pipeline"},"task":{"id":"0f89f601-4337-4b49-846f-5cfe1013daa2","name":"periodic-task-Business","version":"1.0","params":{"param1":"whatever"}},"workspace":{"id":"879e8368-5b2d-4ac4-b145-e0cc22c27447","name":"periodic"},"environment":{"id":"8fc6c8d4-618c-4a0b-96e6-92a4f94ab6d3","name":"prod"},"engine":{"id":"fcc66dfb-232d-4ef2-b8f9-a5dd7c7f8b8c","name":"prod-engine-1","type":"cloud"},"cluster":{"id":"bc803be1-b81c-4a39-a23b-e92bc301ad11","name":"cluster-prod","runProfile":""},"tags":[],"runType":"scheduled"},"fingerprint":{"cpu":{"min":12,"max":83,"mean":33},"memory":{"min":24,"max":145,"mean":60},"logs":[{"timestamp":1585900800000,"cpu":0,"memory":0},{"timestamp":1585900920000,"cpu":74,"memory":33},{"timestamp":1585901040000,"cpu":29,"memory":72},{"timestamp":1585901160000,"cpu":34,"memory":114},{"timestamp":1585901280000,"cpu":49,"memory":107},{"timestamp":1585901400000,"cpu":15,"memory":34},{"timestamp":1585901520000,"cpu":20,"memory":41},{"timestamp":1585901640000,"cpu":40,"memory":53},{"timestamp":1585901760000,"cpu":43,"memory":100},{"timestamp":1585901880000,"cpu":73,"memory":127},{"timestamp":1585902000000,"cpu":59,"memory":33},{"timestamp":1585902120000,"cpu":67,"memory":99},{"timestamp":1585902240000,"cpu":38,"memory":69},{"timestamp":1585902360000,"cpu":40,"memory":110},{"timestamp":1585902480000,"cpu":77,"memory":39},{"timestamp":1585902600000,"cpu":82,"memory":123},{"timestamp":1585902720000,"cpu":19,"memory":82},{"timestamp":1585902840000,"cpu":36,"memory":121},{"timestamp":1585902960000,"cpu":22,"memory":72},{"timestamp":1585903080000,"cpu":36,"memory":31},{"timestamp":1585903200000,"cpu":68,"memory":35},{"timestamp":1585903320000,"cpu":70,"memory":101},{"timestamp":1585903440000,"cpu":37,"memory":109},{"timestamp":1585903560000,"cpu":32,"memory":68},{"timestamp":1585903680000,"cpu":16,"memory":108},{"timestamp":1585903800000,"cpu":55,"memory":54},{"timestamp":1585903920000,"cpu":14,"memory":105},{"timestamp":1585904040000,"cpu":69,"memory":28},{"timestamp":1585904160000,"cpu":79,"memory":125},{"timestamp":1585904280000,"cpu":27,"memory":116},{"timestamp":1585904400000,"cpu":65,"memory":40},{"timestamp":1585904520000,"cpu":53,"memory":135},{"timestamp":1585904640000,"cpu":79,"memory":90},{"timestamp":1585904760000,"cpu":74,"memory":67},{"timestamp":1585904880000,"cpu":55,"memory":81},{"timestamp":1585905000000,"cpu":55,"memory":61},{"timestamp":1585905120000,"cpu":30,"memory":83},{"timestamp":1585905240000,"cpu":48,"memory":75},{"timestamp":1585905360000,"cpu":35,"memory":39},{"timestamp":1585905480000,"cpu":30,"memory":79},{"timestamp":1585905600000,"cpu":80,"memory":34},{"timestamp":1585905720000,"cpu":15,"memory":123},{"timestamp":1585905840000,"cpu":13,"memory":27},{"timestamp":1585905960000,"cpu":76,"memory":62},{"timestamp":1585906080000,"cpu":22,"memory":26},{"timestamp":1585906200000,"cpu":14,"memory":47},{"timestamp":1585906320000,"cpu":57,"memory":67},{"timestamp":1585906440000,"cpu":27,"memory":143},{"timestamp":1585906560000,"cpu":15,"memory":54},{"timestamp":1585906680000,"cpu":69,"memory":88},{"timestamp":1585906800000,"cpu":0,"memory":0}]}}]}