{"timeRange":[1586134800000,1586138400000],"engine":"prod-engine-1","executions":[{"time":{"start":1586131200000,"deploy":1586131238786,"undeploy":1586135124663,"end":1586135149208},"duration":{"deploy":10776,"execution":3885877,"undeploy":52555,"total":3949208},"status":{"management":"undeploy_failure","execution":"successful"},"layout":[{"componentId":"511327e9-7594-4738-a0c9-5f865ec3ea20","status":"","nbRows":0,"nbRejectedRows":0,"duration":0,"error":""},{"componentId":"9179752e-5b09-45a5-9f1b-03ca5ed1a53f","status":"","nbRows":0,"nbRejectedRows":0,"duration":0,"error":""}],"context":{"executionId":"c4dd99f2-f778-4f95-a84d-03bce1938b77","artifact":{"id":"58392c2e-c67b-4be6-b7ab-76db41cf02d9","name":"Business","version":"2.1","type":"pipeline"},"task":{"id":"0c6e9613-6ea0-4b38-9b92-a0f156ee00e6","name":"periodic-task-Business","version":"1.0","params":{"param1":"whatever"}},"workspace":{"id":"d5f13b1d-4602-4cbc-b207-a871ce978387","name":"periodic"},"environment":{"id":"27fdf8c9-962e-4a89-b614-6be5c4309b40","name":"prod"},"engine":{"id":"d99fd702-b9d7-4e71-9c3e-73a93341f4b5","name":"prod-engine-1","type":"cloud"},"cluster":{"id":"4c9cc51e-1667-423a-95ae-e70d20bf1735","name":"cluster-prod","runProfile":""},"tags":[],"runType":"scheduled"},"fingerprint":{"cpu":{"min":12,"max":86,"mean":23},"memory":{"min":16,"max":118,"mean":66},"logs":[{"timestamp":1586131200000,"cpu":0,"memory":0},{"timestamp":1586131320000,"cpu":26,"memory":117},{"timestamp":1586131440000,"cpu":41,"memory":110},{"timestamp":1586131560000,"cpu":75,"memory":32},{"timestamp":1586131680000,"cpu":34,"memory":53},{"timestamp":1586131800000,"cpu":62,"memory":94},{"timestamp":1586131920000,"cpu":28,"memory":47},{"timestamp":1586132040000,"cpu":56,"memory":25},{"timestamp":1586132160000,"cpu":40,"memory":76},{"timestamp":1586132280000,"cpu":19,"memory":98},{"timestamp":1586132400000,"cpu":41,"memory":84},{"timestamp":1586132520000,"cpu":49,"memory":34},{"timestamp":1586132640000,"cpu":72,"memory":78},{"timestamp":1586132760000,"cpu":15,"memory":25},{"timestamp":1586132880000,"cpu":30,"memory":55},{"timestamp":1586133000000,"cpu":46,"memory":17},{"timestamp":1586133120000,"cpu":40,"memory":102},{"timestamp":1586133240000,"cpu":56,"memory":21},{"timestamp":1586133360000,"cpu":28,"memory":81},{"timestamp":1586133480000,"cpu":73,"memory":42},{"timestamp":1586133600000,"cpu":17,"memory":23},{"timestamp":1586133720000,"cpu":51,"memory":30},{"timestamp":1586133840000,"cpu":76,"memory":79},{"timestamp":1586133960000,"cpu":42,"memory":115},{"timestamp":1586134080000,"cpu":30,"memory":52},{"timestamp":1586134200000,"cpu":77,"memory":73},{"timestamp":1586134320000,"cpu":44,"memory":106},{"timestamp":1586134440000,"cpu":48,"memory":86},{"timestamp":1586134560000,"cpu":64,"memory":35},{"timestamp":1586134680000,"cpu":13,"memory":59},{"timestamp":1586134800000,"cpu":63,"memory":43},{"timestamp":1586134920000,"cpu":81,"memory":96},{"timestamp":1586135040000,"cpu":0,"memory":0}]}}]}